LICENSE
dj_iconify/__init__.py
dj_iconify/apps.py
dj_iconify/conf.py
dj_iconify/types.py
dj_iconify/urls.py
dj_iconify/util.py
dj_iconify/views.py
django_iconify-0.4.1.dist-info/LICENSE
django_iconify-0.4.1.dist-info/METADATA
django_iconify-0.4.1.dist-info/WHEEL
django_iconify-0.4.1.dist-info/RECORD
