Metadata-Version: 2.1
Name: django-iconify
Version: 0.4.1
Summary: Iconify API implementation and tools for Django projects
Home-page: https://edugit.org/AlekSIS/libs/django-iconify
License: Apache-2.0
Keywords: iconify,icons,svg,django
Author: Dominik George
Author-email: dominik.george@teckids.org
Requires-Python: >=3.10,<4.0
Classifier: Development Status :: 4 - Beta
Classifier: Environment :: Web Environment
Classifier: Framework :: Django
Classifier: Intended Audience :: Developers
Classifier: License :: OSI Approved :: Apache Software License
Classifier: Programming Language :: Python :: 3
Classifier: Programming Language :: Python :: 3.10
Classifier: Programming Language :: Python :: 3.11
Classifier: Programming Language :: Python :: 3.12
Requires-Dist: Django (>4.2,<6.0)
Project-URL: Repository, https://edugit.org/AlekSIS/libs/django-iconify
